CHANGELOG.md
MANIFEST.in
Pipfile
README.md
setup.cfg
setup.py
apol_dataviz/__init__.py
apol_dataviz/colab.py
apol_dataviz/colors.py
apol_dataviz/formatters.py
apol_dataviz/palette_generators.py
apol_dataviz/plots.py
apol_dataviz/style.py
apol_dataviz/fonts/lato.zip
apolitical_data_viz.egg-info/PKG-INFO
apolitical_data_viz.egg-info/SOURCES.txt
apolitical_data_viz.egg-info/dependency_links.txt
apolitical_data_viz.egg-info/requires.txt
apolitical_data_viz.egg-info/top_level.txt