Metadata-Version: 2.1
Name: apolitical-data-viz
Version: 1.1.0
Summary: Styleguide/utilities for plotting data in the style of apolitical.co
Home-page: UNKNOWN
Author: PaddyAlton
Author-email: paddy.alton@apolitical.co
License: UNKNOWN
Download-URL: https://github.com/apolitical/apolitical-data-viz/archive/v1.1.0.tar.gz
Platform: UNKNOWN
